ucs_detect/__init__.py
ucs_detect/error_matcher.py
ucs_detect/measure.py
ucs_detect/table_vs15.py
ucs_detect/table_vs16.py
ucs_detect/table_wide.py
ucs_detect/table_zwj.py
ucs_detect/terminal.py
ucs_detect/zwj_table.py
ucs_detect/udhr/udhr_007.txt
ucs_detect/udhr/udhr_008.txt
ucs_detect/udhr/udhr_009.txt
ucs_detect/udhr/udhr_010.txt
ucs_detect/udhr/udhr_011.txt
ucs_detect/udhr/udhr_013.txt
ucs_detect/udhr/udhr_014.txt
ucs_detect/udhr/udhr_016.txt
ucs_detect/udhr/udhr_017.txt
ucs_detect/udhr/udhr_020.txt
ucs_detect/udhr/udhr_021.txt
ucs_detect/udhr/udhr_022.txt
ucs_detect/udhr/udhr_023.txt
ucs_detect/udhr/udhr_025.txt
ucs_detect/udhr/udhr_026.txt
ucs_detect/udhr/udhr_027.txt
ucs_detect/udhr/udhr_028.txt
ucs_detect/udhr/udhr_029.txt
ucs_detect/udhr/udhr_030.txt
ucs_detect/udhr/udhr_032.txt
ucs_detect/udhr/udhr_041.txt
ucs_detect/udhr/udhr_042.txt
ucs_detect/udhr/udhr_043.txt
ucs_detect/udhr/udhr_044.txt
ucs_detect/udhr/udhr_045.txt
ucs_detect/udhr/udhr_046.txt
ucs_detect/udhr/udhr_047.txt
ucs_detect/udhr/udhr_048.txt
ucs_detect/udhr/udhr_049.txt
ucs_detect/udhr/udhr_050.txt
ucs_detect/udhr/udhr_052.txt
ucs_detect/udhr/udhr_053.txt
ucs_detect/udhr/udhr_054.txt
ucs_detect/udhr/udhr_055.txt
ucs_detect/udhr/udhr_056.txt
ucs_detect/udhr/udhr_057.txt
ucs_detect/udhr/udhr_058.txt
ucs_detect/udhr/udhr_059.txt
ucs_detect/udhr/udhr_060.txt
ucs_detect/udhr/udhr_061.txt
ucs_detect/udhr/udhr_062.txt
ucs_detect/udhr/udhr_063.txt
ucs_detect/udhr/udhr_064.txt
ucs_detect/udhr/udhr_065.txt
ucs_detect/udhr/udhr_066.txt
ucs_detect/udhr/udhr_067.txt
ucs_detect/udhr/udhr_068.txt
ucs_detect/udhr/udhr_069.txt
ucs_detect/udhr/udhr_071.txt
ucs_detect/udhr/udhr_aar.txt
ucs_detect/udhr/udhr_abk.txt
ucs_detect/udhr/udhr_ace.txt
ucs_detect/udhr/udhr_acu.txt
ucs_detect/udhr/udhr_acu_1.txt
ucs_detect/udhr/udhr_ada.txt
ucs_detect/udhr/udhr_ady.txt
ucs_detect/udhr/udhr_afr.txt
ucs_detect/udhr/udhr_agr.txt
ucs_detect/udhr/udhr_aii.txt
ucs_detect/udhr/udhr_ajg.txt
ucs_detect/udhr/udhr_aka_akuapem.txt
ucs_detect-1.0.8.dist-info/licenses/LICENSE
ucs_detect-1.0.8.dist-info/METADATA
ucs_detect-1.0.8.dist-info/WHEEL
ucs_detect-1.0.8.dist-info/entry_points.txt
ucs_detect-1.0.8.dist-info/top_level.txt
ucs_detect-1.0.8.dist-info/zip-safe
ucs_detect-1.0.8.dist-info/RECORD
