Metadata-Version: 2.4
Name: ucs_detect
Version: 1.0.8
Summary: Detects Unicode support of an interactive terminal
Home-page: https://github.com/jquast/ucs-detect
Author: Jeff Quast
Author-email: contact@jeffquast.com
License: MIT
Keywords: cjk,combining,console,eastasian,emojiemulator,terminal,udhrunicode,vs15,vs16,wcswidth,wcwidth,xterm,zwj
Classifier: Intended Audience :: Developers
Classifier: Natural Language :: English
Classifier: Development Status :: 5 - Production/Stable
Classifier: Environment :: Console
Classifier: License :: OSI Approved :: MIT License
Classifier: Operating System :: POSIX
Classifier: Programming Language :: Python :: 3.8
Classifier: Programming Language :: Python :: 3.9
Classifier: Programming Language :: Python :: 3.10
Classifier: Programming Language :: Python :: 3.11
Classifier: Programming Language :: Python :: 3.12
Classifier: Topic :: Software Development :: Libraries
Classifier: Topic :: Software Development :: Localization
Classifier: Topic :: Software Development :: Internationalization
Classifier: Topic :: Terminals
Classifier: Topic :: Text Processing :: General
Requires-Python: >=3.8
License-File: LICENSE
Requires-Dist: blessed<2,>=1.23
Requires-Dist: wcwidth<1
Requires-Dist: PyYaml<7
Dynamic: author
Dynamic: author-email
Dynamic: classifier
Dynamic: description
Dynamic: home-page
Dynamic: keywords
Dynamic: license
Dynamic: license-file
Dynamic: requires-dist
Dynamic: requires-python
Dynamic: summary
